mojo/taskplus/__init__.py
mojo/taskplus/cli/__init__.py
mojo/taskplus/cli/cmdtree/__init__.py
mojo/taskplus/cli/cmdtree/workflow.py
mojo/taskplus/cli/taskpluscommand.py
mojo/taskplus/entrypoints.py
mojo/taskplus/execution.py
mojo/taskplus/tasks/__init__.py
mojo/taskplus/tasks/createenvironment.py
mojo/taskplus/tasks/embeddedpython.py
mojo/taskplus/tasks/gitcheckout.py
mojo/taskplus/tasks/runcommand.py
mojo/taskplus/tasks/shellscript.py
mojo/taskplus/tasks/taskbase.py
mojo_taskplus-0.0.1.dist-info/WHEEL
mojo_taskplus-0.0.1.dist-info/LICENSE.txt
mojo_taskplus-0.0.1.dist-info/METADATA
mojo_taskplus-0.0.1.dist-info/RECORD
