Metadata-Version: 2.1
Name: mojo-taskplus
Version: 0.0.1
Summary: Automation Mojo Task Plus Library
License: LICENSE.txt
Keywords: python
Requires-Python: >=3.8,<4.0
Classifier: License :: OSI Approved :: MIT License
Classifier: License :: Other/Proprietary License
Classifier: Operating System :: POSIX
Classifier: Programming Language :: Python :: 3
Classifier: Programming Language :: Python :: 3.8
Classifier: Programming Language :: Python :: 3.9
Classifier: Programming Language :: Python :: 3.10
Classifier: Programming Language :: Python :: 3.11
Classifier: Programming Language :: Python :: 3
Requires-Dist: click (>=8.1.3,<9.0.0)
Requires-Dist: mojo-runtime (>=0.0.14,<0.0.15)
